pg_grant/__init__.py
pg_grant/exc.py
pg_grant/parse.py
pg_grant/query.py
pg_grant/sql.py
pg_grant/types.py
tests/query/__init__.py
tests/query/test_columns.py
tests/query/test_database.py
tests/query/test_function.py
tests/query/test_language.py
tests/query/test_schema.py
tests/query/test_sequence.py
tests/query/test_table.py
tests/query/test_tablespace.py
tests/query/test_type.py
pg_grant-0.4.0.dist-info/LICENSE
pg_grant-0.4.0.dist-info/METADATA
pg_grant-0.4.0.dist-info/WHEEL
pg_grant-0.4.0.dist-info/top_level.txt
pg_grant-0.4.0.dist-info/RECORD
