Metadata-Version: 2.1
Name: pg-grant
Version: 0.4.0
Summary: Parse PostgreSQL privileges
Home-page: https://github.com/RazerM/pg_grant
Author: Frazer McLean
Author-email: frazer@frazermclean.co.uk
License: MIT
Classifier: Development Status :: 4 - Beta
Classifier: License :: OSI Approved :: MIT License
Classifier: Programming Language :: Python :: 3
Requires-Python: >=3.6
License-File: LICENSE
Requires-Dist: attrs
Requires-Dist: typing ; python_version<"3.5"
Provides-Extra: docstest
Requires-Dist: doc8 ; extra == 'docstest'
Requires-Dist: sphinx ; extra == 'docstest'
Requires-Dist: sphinx-rtd-theme ; extra == 'docstest'
Provides-Extra: pep8test
Requires-Dist: flake8 ; extra == 'pep8test'
Requires-Dist: pep8-naming ; extra == 'pep8test'
Provides-Extra: sqlalchemy
Requires-Dist: sqlalchemy[postgresql] (>=1.4) ; extra == 'sqlalchemy'
Provides-Extra: test
Requires-Dist: plumbum ; extra == 'test'
Requires-Dist: pytest (>=3.0) ; extra == 'test'
